ai_trello_extract/__init__.py
ai_trello_extract/conftest.py
ai_trello_extract/encoding.py
ai_trello_extract/env_variables.py
ai_trello_extract/env_variables_test.py
ai_trello_extract/functions.py
ai_trello_extract/clients/__init__.py
ai_trello_extract/clients/trello_client.py
ai_trello_extract/clients/trello_client_test.py
ai_trello_extract/dataclasses/__init__.py
ai_trello_extract/dataclasses/categorized_list.py
ai_trello_extract/dataclasses/trello_card.py
ai_trello_extract/formatters/__init__.py
ai_trello_extract/formatters/escape_markdown.py
ai_trello_extract/formatters/escape_markdown_test.py
ai_trello_extract/formatters/generate_markdown.py
ai_trello_extract/formatters/generate_markdown_test.py
ai_trello_extract/orchestrators/__init__.py
ai_trello_extract/orchestrators/orchestration_service.py
ai_trello_extract/orchestrators/orchestration_service_test.py
ai_trello_extract/services/__init__.py
ai_trello_extract/services/trello_service.py
ai_trello_extract/services/trello_service_test.py
ai_trello_extract/services/trello_utilities.py
ai_trello_extract-0.0.9.dist-info/METADATA
ai_trello_extract-0.0.9.dist-info/WHEEL
ai_trello_extract-0.0.9.dist-info/licenses/LICENSE
ai_trello_extract-0.0.9.dist-info/RECORD
