Metadata-Version: 2.3
Name: ai-trello-extract
Version: 0.0.9
Summary: Trello Extract is a Python project that uses the py-trello library and python-dotenv to authenticate with the Trello API and fetch details from Trello boards, lists, and cards. This project demonstrates how to securely manage API credentials and interact with Trello's API to retrieve project data for further processing.
Project-URL: repository, https://github.com/DEV3L/open-ai-assistant
Author-email: Justin Beall <jus.beall@gmail.com>
License: /*
License-File: LICENSE
Keywords: 
Classifier: Development Status :: 4 - Beta
Classifier: Intended Audience :: Developers
Classifier: License :: OSI Approved :: MIT License
Classifier: Programming Language :: Python :: 3
Classifier: Programming Language :: Python :: 3.12
Classifier: Topic :: Software Development :: Libraries :: Python Modules
Requires-Python: >=3.12
Requires-Dist: loguru
Requires-Dist: py-trello-api
Requires-Dist: python-dotenv
Requires-Dist: twine
